uqlm/__init__.py
uqlm/black_box/__init__.py
uqlm/black_box/baseclass/__init__ .py
uqlm/black_box/baseclass/similarity_scorer.py
uqlm/black_box/bert.py
uqlm/black_box/consistency.py
uqlm/black_box/cosine.py
uqlm/black_box/match.py
uqlm/calibration/__init__.py
uqlm/calibration/evaluate.py
uqlm/calibration/score_calibrator.py
uqlm/judges/__init__.py
uqlm/judges/judge.py
uqlm/longform/__init__.py
uqlm/longform/benchmark/__init__.py
uqlm/longform/benchmark/factscore_grader.py
uqlm/longform/decomposition/__init__.py
uqlm/longform/decomposition/response_decomposer.py
uqlm/longform/graph/__init__.py
uqlm/longform/graph/claim_merger.py
uqlm/longform/graph/graph_scorer.py
uqlm/longform/luq/__init__.py
uqlm/longform/luq/baseclass/__init__.py
uqlm/longform/luq/baseclass/claims_scorer.py
uqlm/longform/luq/matched_unit.py
uqlm/longform/luq/unit_response.py
uqlm/longform/qa/__init__.py
uqlm/longform/qa/question_generator.py
uqlm/longform/uad/__init__.py
uqlm/longform/uad/uad.py
uqlm/nli/__init__.py
uqlm/nli/cluster.py
uqlm/nli/entailment.py
uqlm/nli/nli.py
uqlm/resources/__init__.py
uqlm/scorers/__init__.py
uqlm/scorers/baseclass/__init__.py
uqlm/scorers/baseclass/uncertainty.py
uqlm/scorers/longform/__init__.py
uqlm/scorers/longform/baseclass/__init__.py
uqlm/scorers/longform/baseclass/uncertainty.py
uqlm/scorers/longform/graph.py
uqlm/scorers/longform/longtext.py
uqlm/scorers/longform/qa.py
uqlm/scorers/shortform/__init__.py
uqlm/scorers/shortform/baseclass/__init__.py
uqlm/scorers/shortform/baseclass/uncertainty.py
uqlm/scorers/shortform/black_box.py
uqlm/scorers/shortform/density.py
uqlm/scorers/shortform/ensemble.py
uqlm/scorers/shortform/entropy.py
uqlm/scorers/shortform/panel.py
uqlm/scorers/shortform/white_box.py
uqlm/utils/__init__.py
uqlm/utils/dataloader.py
uqlm/utils/device.py
uqlm/utils/display.py
uqlm/utils/grader.py
uqlm/utils/llm_config.py
uqlm/utils/plots.py
uqlm/utils/postprocessors.py
uqlm/utils/prompts/__init__.py
uqlm/utils/prompts/claim_qa.py
uqlm-0.5.4.dist-info/LICENSE
uqlm-0.5.4.dist-info/METADATA
uqlm-0.5.4.dist-info/WHEEL
uqlm-0.5.4.dist-info/RECORD
