Metadata-Version: 2.1
Name: uqlm
Version: 0.5.4
Summary: UQLM (Uncertainty Quantification for Language Models) is a Python package for UQ-based LLM hallucination detection.
Home-page: https://github.com/cvs-health/uqlm
License: Apache-2.0
Keywords: LLM,large language model,LLM evaluation,hallucination,uncertainty quantification
Author: Dylan Bouchard
Author-email: dylan.bouchard@cvshealth.com
Maintainer: Dylan Bouchard
Maintainer-email: dbouchard92@gmail.com
Requires-Python: >=3.10,<4.0
Classifier: License :: OSI Approved :: Apache Software License
Classifier: Operating System :: OS Independent
Classifier: Programming Language :: Python :: 3
Classifier: Programming Language :: Python :: 3.10
Classifier: Programming Language :: Python :: 3.11
Classifier: Programming Language :: Python :: 3.12
Classifier: Programming Language :: Python :: 3.13
Classifier: Programming Language :: Python :: 3 :: Only
Classifier: Topic :: Scientific/Engineering :: Artificial Intelligence
Classifier: Topic :: Software Development :: Libraries :: Python Modules
Requires-Dist: bert-score (>=0.3.0,<0.4.0)
Requires-Dist: datasets (>=3.3.2,<5.0.0)
Requires-Dist: ipywidgets (>=8.1.7,<9.0.0)
Requires-Dist: langchain (>=0.3.7)
Requires-Dist: langchain-model-profiles (>=0.0.3,<0.0.4)
Requires-Dist: matplotlib (>=3.10.0,<4.0.0)
Requires-Dist: numpy (>=1.26.4,<2.0.0) ; python_version < "3.13"
Requires-Dist: numpy (>=2.3.1) ; python_version >= "3.13"
Requires-Dist: optuna (>=4.0.0,<5.0.0)
Requires-Dist: pandas (>=2.3.0,<3.0.0)
Requires-Dist: rich (>=13.8.0,<14.0.0)
Requires-Dist: scikit-learn (>=1.5.2,<2.0.0) ; python_version < "3.13"
Requires-Dist: scikit-learn (>=1.7.0,<2.0.0) ; python_version >= "3.13"
Requires-Dist: scipy (>=1.15.0,<2.0.0) ; python_version >= "3.13"
Requires-Dist: sentence-transformers (>=3.4,<6.0)
Requires-Dist: transformers (>=4.45.2,<5.0.0)
Project-URL: Documentation, https://cvs-health.github.io/uqlm/latest/index.html
Project-URL: Repository, https://github.com/cvs-health/uqlm
